FreebsdShiyongshouce/README.md
FreebsdShiyongshouce/__init__.py
FreebsdShiyongshouce/__main__.py
FreebsdShiyongshouce/file.epub
FreebsdShiyongshouce/index.html
FreebsdShiyongshouce/css/__init__.py
FreebsdShiyongshouce/css/annotations.css
FreebsdShiyongshouce/css/main.css
FreebsdShiyongshouce/css/normalize.css
FreebsdShiyongshouce/css/popup.css
FreebsdShiyongshouce/font/__init__.py
FreebsdShiyongshouce/font/fontello.eot
FreebsdShiyongshouce/font/fontello.svg
FreebsdShiyongshouce/font/fontello.ttf
FreebsdShiyongshouce/font/fontello.woff
FreebsdShiyongshouce/img/__init__.py
FreebsdShiyongshouce/img/annotator-glyph-sprite.png
FreebsdShiyongshouce/img/annotator-icon-sprite.png
FreebsdShiyongshouce/img/apple-touch-icon.png
FreebsdShiyongshouce/img/cancelfullscreen.png
FreebsdShiyongshouce/img/close.png
FreebsdShiyongshouce/img/fullscreen.png
FreebsdShiyongshouce/img/loader.gif
FreebsdShiyongshouce/img/menu-icon.png
FreebsdShiyongshouce/img/save.png
FreebsdShiyongshouce/img/saved.png
FreebsdShiyongshouce/img/settings-s.png
FreebsdShiyongshouce/img/settings.png
FreebsdShiyongshouce/img/star.png
FreebsdShiyongshouce/js/__init__.py
FreebsdShiyongshouce/js/epub.js
FreebsdShiyongshouce/js/epub.min.js
FreebsdShiyongshouce/js/epub.min.map
FreebsdShiyongshouce/js/hooks.min.js
FreebsdShiyongshouce/js/hooks.min.map
FreebsdShiyongshouce/js/reader.js
FreebsdShiyongshouce/js/reader.js.map
FreebsdShiyongshouce/js/reader.min.js
FreebsdShiyongshouce/js/reader.min.map
FreebsdShiyongshouce/js/hooks/__init__.py
FreebsdShiyongshouce/js/hooks/extensions/__init__.py
FreebsdShiyongshouce/js/hooks/extensions/highlight.js
FreebsdShiyongshouce/js/libs/__init__.py
FreebsdShiyongshouce/js/libs/jquery.min.js
FreebsdShiyongshouce/js/libs/localforage.min.js
FreebsdShiyongshouce/js/libs/screenfull.js
FreebsdShiyongshouce/js/libs/screenfull.min.js
FreebsdShiyongshouce/js/libs/zip.min.js
FreebsdShiyongshouce/js/plugins/__init__.py
FreebsdShiyongshouce/js/plugins/hypothesis.js
freebsd_shiyongshouce-2024.3.1.0.dist-info/METADATA
freebsd_shiyongshouce-2024.3.1.0.dist-info/WHEEL
freebsd_shiyongshouce-2024.3.1.0.dist-info/entry_points.txt
freebsd_shiyongshouce-2024.3.1.0.dist-info/top_level.txt
freebsd_shiyongshouce-2024.3.1.0.dist-info/RECORD
